{
  "data": [
    {
      "id": "69d376ce-ce4e-4a03-bc5c-63d8bbfdf99e",
      "url": "verge.com",
      "username": "ijo",
      "password": "2345aBb!3",
      "created_at": "2017-05-26T10:50:26.223Z"
    },
    {
      "id": "9c50dc4d-4578-465a-a5ce-df6c12b0f9ba",
      "url": "www.google.com",
      "username": "john",
      "password": "haha",
      "created_at": "2017-05-26T10:53:22.887Z",
      "updated_at": "2017-05-28T10:01:33.525Z"
    },
    {
      "id": "ec9491ac-afe6-47be-8bf4-0eea98450865",
      "url": "warriors.com",
      "username": "curry",
      "password": "haha",
      "created_at": "2017-05-28T04:42:32.493Z",
      "updated_at": "2017-05-28T04:48:48.062Z"
    },
    {
      "id": "bc4ecaec-3c4c-4c40-80a5-ed66ce54c8a6",
      "url": "test",
      "username": "ijo",
      "password": "13B!!1d",
      "created_at": "2017-05-28T11:54:12.103Z"
    }
  ]
}